codemap/__init__.py
codemap/__main__.py
codemap/config.py
codemap/cli/__init__.py
codemap/cli/commit_cmd.py
codemap/cli/gen_cmd.py
codemap/cli/pr_cmd.py
codemap/gen/__init__.py
codemap/gen/command.py
codemap/gen/generator.py
codemap/gen/models.py
codemap/gen/utils.py
codemap/git/__init__.py
codemap/git/interactive.py
codemap/git/utils.py
codemap/git/commit_generator/__init__.py
codemap/git/commit_generator/command.py
codemap/git/commit_generator/generator.py
codemap/git/commit_generator/prompts.py
codemap/git/commit_generator/schemas.py
codemap/git/commit_generator/utils.py
codemap/git/commit_linter/__init__.py
codemap/git/commit_linter/config.py
codemap/git/commit_linter/constants.py
codemap/git/commit_linter/linter.py
codemap/git/commit_linter/parser.py
codemap/git/commit_linter/validators.py
codemap/git/diff_splitter/__init__.py
codemap/git/diff_splitter/constants.py
codemap/git/diff_splitter/schemas.py
codemap/git/diff_splitter/splitter.py
codemap/git/diff_splitter/strategies.py
codemap/git/diff_splitter/utils.py
codemap/git/pr_generator/__init__.py
codemap/git/pr_generator/command.py
codemap/git/pr_generator/constants.py
codemap/git/pr_generator/decorators.py
codemap/git/pr_generator/generator.py
codemap/git/pr_generator/prompts.py
codemap/git/pr_generator/schemas.py
codemap/git/pr_generator/strategies.py
codemap/git/pr_generator/templates.py
codemap/git/pr_generator/utils.py
codemap/llm/__init__.py
codemap/llm/api.py
codemap/llm/client.py
codemap/llm/config.py
codemap/llm/errors.py
codemap/llm/utils.py
codemap/processor/README.md
codemap/processor/__init__.py
codemap/processor/lod.py
codemap/processor/pipeline.py
codemap/processor/tree_sitter/TODO.md
codemap/processor/tree_sitter/__init__.py
codemap/processor/tree_sitter/analyzer.py
codemap/processor/tree_sitter/base.py
codemap/processor/tree_sitter/languages/__init__.py
codemap/processor/tree_sitter/languages/base.py
codemap/processor/tree_sitter/languages/javascript.py
codemap-2.0.0.dist-info/METADATA
codemap-2.0.0.dist-info/WHEEL
codemap-2.0.0.dist-info/entry_points.txt
codemap-2.0.0.dist-info/licenses/LICENSE
codemap-2.0.0.dist-info/RECORD
