Metadata-Version: 2.4
Name: codemap
Version: 2.0.0
Summary: CLI tool that generates optimized markdown docs and streamline Git workflows
Author-email: Sarthak Mishra <hi@sarthakmishra.com>
License: MIT
License-File: LICENSE
Keywords: cli,codebase,documentation,git,markdown
Requires-Python: <3.13,>=3.12
Requires-Dist: fastapi>=0.110.0
Requires-Dist: lancedb>=0.21.2
Requires-Dist: litellm>=1.67.0
Requires-Dist: lockfile>=0.12.2
Requires-Dist: multilspy>=0.0.15
Requires-Dist: numpy>=2.2.5
Requires-Dist: packaging>=24.2
Requires-Dist: pandas>=2.2.3
Requires-Dist: pathspec>=0.12.1
Requires-Dist: pydantic>=2.7.0
Requires-Dist: pygments>=2.19.1
Requires-Dist: pytest-mock>=3.14.0
Requires-Dist: python-daemon>=3.1.2
Requires-Dist: python-dotenv>=1.1.0
Requires-Dist: pyxdg>=0.28
Requires-Dist: pyyaml>=6.0.2
Requires-Dist: questionary>=2.1.0
Requires-Dist: requests-unixsocket>=0.4.1
Requires-Dist: requests>=2.32.3
Requires-Dist: rich>=14.0.0
Requires-Dist: sentence-transformers>=4.1.0
Requires-Dist: tree-sitter-language-pack>=0.7.2
Requires-Dist: tree-sitter>=0.24.0
Requires-Dist: typer>=0.15.2
Requires-Dist: typing-extensions>=4.13.2
Requires-Dist: uvicorn>=0.29.0
Requires-Dist: watchdog>=6.0.0
